ilulab/__init__.py
ilulab/client.py
ilulab-0.0.4.dist-info/METADATA
ilulab-0.0.4.dist-info/WHEEL
ilulab-0.0.4.dist-info/licenses/LICENSE
ilulab-0.0.4.dist-info/RECORD
